ddgen/__init__.py
ddgen/test_db.py
ddgen/test_utils.py
ddgen/db/__init__.py
ddgen/db/h2.py
ddgen/db/jar/h2-1.4.199.jar
ddgen/db/jar/h2-1.4.200.jar
ddgen/test_data/hg19_sv_database.mv.db
ddgen/utils/__init__.py
ddgen/utils/_effects.py
ddgen/utils/_intervals.py
ddgen/utils/_logging.py
ddgen/utils/_txs.py
ddgen/utils/test__effects.py
ddgen/utils/test__intervals.py
ddgen/utils/test__logging.py
ddgen/utils/test__txs.py
ddgen/utils/data/hg19.dict
ddgen/utils/data/hg38.dict
ddgen/utils/test_data/test.dict
ddgen-0.0.10.post1.data/data/requirements.txt
ddgen-0.0.10.post1.dist-info/LICENSE
ddgen-0.0.10.post1.dist-info/METADATA
ddgen-0.0.10.post1.dist-info/WHEEL
ddgen-0.0.10.post1.dist-info/top_level.txt
ddgen-0.0.10.post1.dist-info/RECORD
