Metadata-Version: 2.1
Name: ddgen
Version: 0.0.10.post1
Summary: Library of Python utilities that I needed so many times
Home-page: https://github.com/ielis/ddgen
Author: Daniel Danis
Author-email: daniel.gordon.danis@gmail.com
License: GPLv3
Keywords: bioinformatics genomics
Platform: UNKNOWN
Requires-Dist: pandas (>=1.0.3)
Requires-Dist: numpy (>=1.18.2)
Requires-Dist: psycopg2-binary (>=2.8.4)
